kafka_processor/__init__.py
kafka_processor/enhanced_list.py
kafka_processor/exceptions.py
kafka_processor/kafka_processor.py
kafka_processor/kafka_processor_consumer.py
kafka_processor/kafka_processor_producer.py
kafka_processor/processing_flow.py
kafka_processor/metrics/__init__.py
kafka_processor/metrics/consumer_metrics.py
kafka_processor/metrics/kafka_processor_metrics.py
kafka_processor/metrics/metrics_types.py
kafka_processor/metrics/producer_metrics.py
kafka_processor-0.0.7.dist-info/LICENSE
kafka_processor-0.0.7.dist-info/METADATA
kafka_processor-0.0.7.dist-info/WHEEL
kafka_processor-0.0.7.dist-info/top_level.txt
kafka_processor-0.0.7.dist-info/RECORD
