Metadata-Version: 2.1
Name: kafka-processor
Version: 0.0.7
Summary: A package to execute tasks on kafka messages and pass them over
Home-page: https://github.com/shalomnaim1/kafka_processor
Author: Shalom Naim
Author-email: shalom.naim1@gmail.com
License: UNKNOWN
Project-URL: Bug Tracker, https://github.com/shalomnaim1/kafka_processor/issues
Platform: UNKNOWN
Classifier: Programming Language :: Python :: 3
Classifier: License :: OSI Approved :: Apache Software License
Classifier: Programming Language :: Python :: 3.6
Classifier: Programming Language :: Python :: 3.7
Classifier: Programming Language :: Python :: 3.8
Classifier: Programming Language :: Python :: 3.9
Classifier: Programming Language :: Python :: 3.10
Requires-Python: >=3.6
License-File: LICENSE
Requires-Dist: kafka-python (==2.0.2)
Requires-Dist: appmetrics (==0.5.0)
